ezgo/__init__.py
ezgo/camera.py
ezgo/ezcamera.py
ezgo/eztk.py
ezgo/go2.py
ezgo/go2_camera.py
ezgo/go2_vui.py
ezgo/ui.py
ezgo-0.0.15.dist-info/LICENSE
ezgo-0.0.15.dist-info/METADATA
ezgo-0.0.15.dist-info/WHEEL
ezgo-0.0.15.dist-info/top_level.txt
ezgo-0.0.15.dist-info/RECORD
