Metadata-Version: 2.1
Name: ezgo
Version: 0.0.15
Summary: 宇树Go2机器狗Python控制库
Author-email: ezgo <noreply@example.com>
License: MIT
Project-URL: Homepage, https://github.com/your-username/ezgo
Project-URL: Repository, https://github.com/your-username/ezgo
Project-URL: Bug Reports, https://github.com/your-username/ezgo/issues
Keywords: robotics,unitree,go2,robot,control
Classifier: Development Status :: 3 - Alpha
Classifier: Intended Audience :: Developers
Classifier: License :: OSI Approved :: MIT License
Classifier: Operating System :: OS Independent
Classifier: Programming Language :: Python :: 3
Classifier: Programming Language :: Python :: 3.7
Classifier: Programming Language :: Python :: 3.8
Classifier: Programming Language :: Python :: 3.9
Classifier: Programming Language :: Python :: 3.10
Classifier: Programming Language :: Python :: 3.11
Classifier: Topic :: Software Development :: Libraries :: Python Modules
Requires-Python: >=3.7
License-File: LICENSE
Provides-Extra: basic
Requires-Dist: opencv-python>=4.5.0; extra == "basic"
Requires-Dist: numpy>=1.19.0; extra == "basic"
Requires-Dist: Pillow>=8.0.0; extra == "basic"
Provides-Extra: full
Requires-Dist: opencv-python>=4.5.0; extra == "full"
Requires-Dist: numpy>=1.19.0; extra == "full"
Requires-Dist: Pillow>=8.0.0; extra == "full"
Requires-Dist: netifaces>=0.10.0; extra == "full"
Requires-Dist: unitree-sdk2py; extra == "full"
